{"card_name": "Call Lightning", "color": "R", "rarity": "cube", "type": "Enchantment", "number": 158, "color_identity": "R", "cost": "{X}{R}", "rules_text": "Call Lightning enters with a charge counter on it for each mana spent to cast it.\nUntap Call Lightning during each player\u2019s untap step.\n{T}, Remove 1 charge counter from Call Lightning: Call Lightning deals 2 damage to any target.\n{T}, Remove 2 charge counters from Call Lightning: Call Lightning deals 3 damage to any target.", "pt": "", "special_text": "", "shape": "normal", "set": "BG3", "loyalty": "", "notes": ""}